lhs_mcp_demov/__init__.py
lhs_mcp_demov-0.1.0.dist-info/WHEEL
lhs_mcp_demov-0.1.0.dist-info/entry_points.txt
lhs_mcp_demov-0.1.0.dist-info/METADATA
lhs_mcp_demov-0.1.0.dist-info/RECORD
