Metadata-Version: 2.3
Name: lhs-mcp-demov
Version: 0.1.0
Summary: Add your description here
Author: lhs
Author-email: lhs <1350371071@qq.com>
Requires-Dist: mcp[cli]>=1.13.1
Requires-Python: >=3.11.5
